shabti_api_client/__init__.py
shabti_api_client/auth_client.py
shabti_api_client/base_client.py
shabti_api_client/client.py
shabti_api_client/codes.py
shabti_api_client/exceptions.py
shabti_api_client/raise_error.py
shabti_api_client-0.1a6.dist-info/METADATA
shabti_api_client-0.1a6.dist-info/WHEEL
shabti_api_client-0.1a6.dist-info/RECORD
