Metadata-Version: 2.4
Name: shabti-api-client
Version: 0.1a6
Requires-Python: >=3.12
Requires-Dist: httpx
Requires-Dist: python-keycloak
Requires-Dist: shabti-types
